{"id": 386, "url": "https://librarynovel.com/novel/super-gene/chapter-384-qigong-master", "title": "Chapter 384 - Qigong Master?", "volume": 4, "volume_title": "Volume 4", "body": "<h1>Chapter 384 - Qigong Master?</h1><p>Chapter 384: Qigong Master?</p><p>Translator: Nyoi-Bo Studio Editor: Nyoi-Bo Studio</p><p>Han Sen did not believe that Ning Yue never looked into his background. Either Han Sen’s great grandfather was a friend to the Nings, or the death of Han Sen’s father had something to do with Starry Group, Ning Yue’s behaviors were strange.</p><p>“What is the name of the friend? Maybe he is in my family,” Han Sen probed with a smile.</p><p>“Han Jingzhi,” Ning Yue said without hesitation.</p><p>“That is such a coincidence. The name of my great-grandfather was also Han Jingzhi. They are not the same person, are they?” Han Sen simply asked. It should be easy for Ning Yue to find out such information, so there was no need to hide.</p><p>Ning Yue said in a gentle manner, “They should not be the same person. The friend of my great-grandfather is much older than your great-grandfather, and he never got married.”</p><p>Han Sen was confused by Ning Yue’s reply, and then understood what was wrong about Zhu Ting’s statement.</p><p>His great-grandfather Han Jingzhi was not even born when God’s Sanctuary was first discovered.</p><p>However, if Han Sen’s great-grandfather was not the friend Ning Yue was talking about, why did he have the work permit?</p><p>Han Sen felt more and more puzzled about what had happened and what Unit 7 had seen in God’s Sanctuary.</p><p>“A friend of the Nings must be a celebrity as well, right?” Han Sen asked.</p><p>Ning Yue smiled and nodded. “Indeed, he is an incredible person. And that age, the God’s Sanctuary was only just discovered. Before mankind started to gain geno points and hyper geno arts were developed, Han Jingzhi was already a famous qigong master.”</p><p>“Qigong master?” Han Sen became dumbstruck. He had learned in history class that the qigong masters were all basically just con artists.</p><p>“It’s not what you think. Han Jingzhi had incredible skills and was the instructor of the Blueblood Special Force,” Ning Yue said with a smile, knowing what Han Sen was thinking.</p><p>“The instructor of the Blueblood Special Force?” Han Sen became more shocked. Blueblood Special Force was still the elite force in the Alliance. Even an ordinary member of the Blueblood Special Force was surpasser. It was easy to tell how good the troop was. The instructor of the Blueblood Special Force at this point was a famous demigod.</p><p>Han Sen became more confused. If his great-grandfather was really the Han Jingzhi whom Ning Yue was talking about, it seemed unlikely for the Hans to be so poor.</p><p>In addition, Han Sen had never heard about any qigong in the family.</p><p>Han Sen wanted to ask more about the Instructor Han, but it was already time to set out on the journey again. Ning Yue got up and told everyone to depart.</p><p>What am I missing? Han Sen felt like he must be missing something in these connections.</p><p>Han Sen had to put the thoughts away because they had already reached the primeval forest. What Han Sen cared most was how to kill the super creature.</p><p>He must kill the super creature, but he could not let the rest of the group see the life essence, which was not something easy to accomplish.</p><p>More importantly, Han Sen did not know much about the creature so far. He had to use Ning Yue’s knowledge of the creature before he could determine whether he could kill it.</p><p>Otherwise, Han Sen would have come back and killed the creature when the group was drugged by Zhu Ting.</p><p>Ning Yue and Han Sen were carefully protected by the three other members, who had already become evolvers. With higher fitness index, they felt the tasks much easier.</p><p>When the group of five came to the mountain again, they climbed up at Ning Yue’s command this time. The mountain was huge, although it was not steep. Han Sen followed the rest of them to go up. When they were about to reach the mountaintop, everyone became careful.</p><p>“Hush!” Yang Yongcheng who was leading the group signaled them to be silent when they were about to reach the mountaintop.</p><p>The mountaintop was a stone platform about half an acre.</p><p>The giant snail with the jade shell and red body was resting, hidden in the shell. The red meat was concealed completely.</p><p>“Young master, Mr. Han, wait here for a second. We will draw it out,” whispered Yang Yongcheng.</p><p>“Be careful. Safety first.” Ning Yue nodded.</p><p>The three evolvers agreed and approached the creature. They summoned beast soul bows and started to shoot Z-steel arrows at the shell.</p><p>Boom boom boom!</p><p>The Z-steel arrows were smashed against the shell. All three revolvers shapeshifted into humanoid figures. With their fitness level as evolvers, they became extremely strong.</p><p>Han Sen checked the way that the Z-steel arrows broke and found that they did not break because the revolvers were strong, but because the jade-like shell seemed to have a bouncing effect, which crushed the arrows.</p><p>Super creatures are never easy. Han Sen thought to himself.</p><p>After taking several arrows, the snail stretched its red meat from the shell and fixed its eyes on the evolvers. All of a sudden, it rushed toward them.</p><p>If it was before, the revolvers would have chosen to keep their distance from the snail. However, this time they must approach the snail to make it leave its shell so that Han Sen could kill it with his dagger.</p><p>In addition, the evolvers felt more confident since they basically represented the strongest humans in First God’s Sanctuary. Therefore, they were not as scared of the creature.</p><p>Very soon, they found that they were too naïve. The strong physique of evolver did not make it easier for them to fight the creature.</p>", "images": {}, "success": true}